{
    "targets": [
        {
            "name": "Total Integrated Target/Direct Integration",
            "temp_pinch": {
                "cold_temp": {
                    "value": 98.0,
                    "units": "degC"
                },
                "hot_temp": {
                    "value": 98.0,
                    "units": "degC"
                }
            },
            "Qh": {
                "value": 11.907701094471832,
                "units": "kW"
            },
            "Qc": {
                "value": 115.36770109447187,
                "units": "kW"
            },
            "Qr": {
                "value": 1832.9122989055284,
                "units": "kW"
            },
            "degree_of_integration": {
                "value": 99.35453317426784,
                "units": "%"
            },
            "utility_cost": {
                "value": 350720098.2718533,
                "units": "$/y"
            },
            "hot_utilities": [
                {
                    "name": "HPS",
                    "heat_flow": {
                        "value": 0.0,
                        "units": "kW"
                    }
                },
                {
                    "name": "MPS",
                    "heat_flow": {
                        "value": 11.907701094471832,
                        "units": "kW"
                    }
                }
            ],
            "cold_utilities": [
                {
                    "name": "CW",
                    "heat_flow": {
                        "value": 23.5682378676236,
                        "units": "kW"
                    }
                },
                {
                    "name": "CHW",
                    "heat_flow": {
                        "value": 91.79946322684827,
                        "units": "kW"
                    }
                }
            ]
        },
        {
            "name": "Plant/Direct Integration",
            "temp_pinch": {
                "cold_temp": {
                    "value": 98.0,
                    "units": "degC"
                },
                "hot_temp": {
                    "value": 98.0,
                    "units": "degC"
                }
            },
            "Qh": {
                "value": 11.907701094471832,
                "units": "kW"
            },
            "Qc": {
                "value": 115.36770109447187,
                "units": "kW"
            },
            "Qr": {
                "value": 1832.9122989055284,
                "units": "kW"
            },
            "degree_of_integration": {
                "value": 99.35453317426784,
                "units": "%"
            },
            "utility_cost": {
                "value": 350720098.2718533,
                "units": "$/y"
            },
            "hot_utilities": [
                {
                    "name": "HPS",
                    "heat_flow": {
                        "value": 0.0,
                        "units": "kW"
                    }
                },
                {
                    "name": "MPS",
                    "heat_flow": {
                        "value": 11.907701094471832,
                        "units": "kW"
                    }
                }
            ],
            "cold_utilities": [
                {
                    "name": "CW",
                    "heat_flow": {
                        "value": 23.5682378676236,
                        "units": "kW"
                    }
                },
                {
                    "name": "CHW",
                    "heat_flow": {
                        "value": 91.79946322684827,
                        "units": "kW"
                    }
                }
            ]
        },
        {
            "name": "Total Process Target/Direct Integration",
            "temp_pinch": {
                "cold_temp": {
                    "value": null,
                    "units": "degC"
                },
                "hot_temp": {
                    "value": null,
                    "units": "degC"
                }
            },
            "Qh": {
                "value": 11.907701094471832,
                "units": "kW"
            },
            "Qc": {
                "value": 115.36770109447187,
                "units": "kW"
            },
            "Qr": {
                "value": 1832.9122989055284,
                "units": "kW"
            },
            "degree_of_integration": {
                "value": null,
                "units": "%"
            },
            "utility_cost": {
                "value": 350720098.2718533,
                "units": "$/y"
            },
            "hot_utilities": [
                {
                    "name": "HPS",
                    "heat_flow": {
                        "value": 0.0,
                        "units": "kW"
                    }
                },
                {
                    "name": "MPS",
                    "heat_flow": {
                        "value": 11.907701094471832,
                        "units": "kW"
                    }
                }
            ],
            "cold_utilities": [
                {
                    "name": "CW",
                    "heat_flow": {
                        "value": 23.5682378676236,
                        "units": "kW"
                    }
                },
                {
                    "name": "CHW",
                    "heat_flow": {
                        "value": 91.79946322684827,
                        "units": "kW"
                    }
                }
            ]
        },
        {
            "name": "Total Site Target/Direct Integration",
            "temp_pinch": {
                "cold_temp": {
                    "value": 92.0,
                    "units": "degC"
                },
                "hot_temp": {
                    "value": 148.9,
                    "units": "degC"
                }
            },
            "Qh": {
                "value": 11.907701094471832,
                "units": "kW"
            },
            "Qc": {
                "value": 115.36770109447187,
                "units": "kW"
            },
            "Qr": {
                "value": 1832.9122989055284,
                "units": "kW"
            },
            "degree_of_integration": {
                "value": 99.35453317426784,
                "units": "%"
            },
            "utility_cost": {
                "value": 350720098.2718533,
                "units": "$/y"
            },
            "hot_utilities": [
                {
                    "name": "HPS",
                    "heat_flow": {
                        "value": 0.0,
                        "units": "kW"
                    }
                },
                {
                    "name": "MPS",
                    "heat_flow": {
                        "value": 11.907701094471832,
                        "units": "kW"
                    }
                }
            ],
            "cold_utilities": [
                {
                    "name": "CW",
                    "heat_flow": {
                        "value": 23.5682378676236,
                        "units": "kW"
                    }
                },
                {
                    "name": "CHW",
                    "heat_flow": {
                        "value": 91.79946322684827,
                        "units": "kW"
                    }
                }
            ]
        }
    ]
}